Workbook

Sheet Portfolio
A1: Project | B1: Status | C1: Merged / parked into | D1: One-line purpose | E1: Category | F1: Form factor | G1: Primary stack (from spec §3) | H1: Runs on | I1: Best use | J1: DCC group | K1: Best path | L1: Open-source fit | M1: Commercial fit | N1: Rationale | O1: GitHub repo | P1: Your notes | Q1: Open questions (REPORT.md)
A2: am-i-underpaid | B2: Merged → feature | C2: jobs-search-and-apply-tool | E2: Career | F2: — | G2: — | H2: — | I2: Feature of host | J2: Career | K2: — | L2: — | M2: — | N2: Comp-check tab that feeds the compensation floor. | O2: https://github.com/snknitin/am-i-underpaid | Q2: —
A3: jobs-search-and-apply-tool | B3: Greenfield · host | C3: absorbs am-i-underpaid | D3: A private, Windows-localhost career operations console for one job seeker: capture roles from user-selected sources (paste + official Greenhouse/Lever/Ashby feeds), rank fit against a versioned target universe with visible hard-gate/score explanations, build truthful application packets where every claim resolves to an approved evidence record, and track applications/follow-ups — with final submission permanently human. It is the upstream producer of the portable career handoffs (`interview-prep.json`, `study-gaps.json`, `calendar-actions.ics`) defined in §4. It absorbs Am I Underpaid as the **Comp check** feature: an honest compensation range (cohort size and dataset year always shown) and sustainable-rate floor that can be proposed as the target universe's compensation floor. | E3: Career | F3: Web dashboard | G3: FastAPI, HTMX, Jinja, DuckDB, Playwright, SQLite, React | H3: Windows desktop | I3: DCC tab | J3: Career | K3: Personal → Commercial | L3: Medium | M3: Medium | N3: Truthful, evidence-gated packets differentiate from auto-apply tools; job seekers pay. | O3: https://github.com/snknitin/jobs-search-and-apply-tool | Q3: 3 blocking · 1 questions · 1 proposals
A4: mock-interview-gauntlet | B4: Greenfield | D4: A private, loopback-only interview simulator for senior technical IC roles (MTS/AI Engineer, Staff/Principal DS, FDE, Research Scientist): an approved job posting plus approved candidate evidence drives bounded practice sessions, evidence-linked AI critique with anchored bands, selective independent verification, and same-scenario retries. It critiques observable reasoning against a versioned rubric. | E4: Career | F4: Web dashboard | G4: FastAPI, Jinja, Playwright, SQLite | H4: Windows desktop (+Spark inference) | I4: DCC tab | J4: Career | K4: Personal → Commercial | L4: Medium | M4: High | N4: Interview prep is a proven paid market; evidence-linked critique without hiring verdicts is a strong angle. | O4: https://github.com/snknitin/mock-interview-gauntlet | Q4: 1 blocking · 1 questions · 2 proposals
A5: resume-blueprint-studio | B5: Greenfield | D5: A local-first Windows web app that turns a resume (PDF/DOCX) into an explorable, source-linked preparation library: faithful page viewer, exploded section/bullet cards in page-side lanes, and connected action cards (Explain, Rephrase, Primer, FAQ, Research, System design, Recall) whose outputs publish as Markdown into the owner's Obsidian Personal Sync vault. Single user; Windows owns all state; Spark supplies inference through an existing route. All 17 confirmed product decisions live in `docs/decisions.json` and are binding. | E5: Career | F5: Web dashboard (React/Vite) | G5: FastAPI, SQLite, React | H5: Windows desktop | I5: DCC tab | J5: Career | K5: Personal | L5: Medium | M5: Medium | N5: Explorable resume prep library; publishes into the vault. | O5: https://github.com/snknitin/resume-blueprint-studio | Q5: 1 blocking · 0 questions · 2 proposals
A6: recruiting-agency | B6: Greenfield | D6: A local hiring-design desk: turn a vague hiring request into an outcome-focused JD, precommitted versioned rubric, channel plan, blind evidence-linked candidate summaries, outreach drafts, and a structured interview kit — with humans recording every decision and override. Decision support, never automated rejection. | E6: Career (employer side) | F6: Web dashboard | G6: SvelteKit, FastAPI, SQLite | H6: Windows desktop | I6: DCC tab | J6: Client services | K6: Commercial | L6: Low | M6: Medium | N6: Hiring-design desk for small teams; decision support, never automated rejection. | O6: https://github.com/snknitin/recruiting-agency | Q6: 0 blocking · 3 questions · 0 proposals
A7: ai-event-matchmaker | B7: Merged → feature | C7: event-ops-agency | E7: Client services | F7: — | G7: — | H7: — | I7: Feature of host | J7: Client services | K7: — | L7: — | M7: — | N7: Attendee matchmaking tab. | O7: https://github.com/snknitin/ai-event-matchmaker | Q7: —
A8: community-ops-agency | B8: Greenfield | D8: A human-supervised operations desk for one community: import rules, members, events, and messages (manual JSON/CSV export), classify activity with evidence, and produce the weekly operating kit — digest, moderation suggestion queue, onboarding page, ICS calendar, unanswered-question tracker, and three low-pressure engagement prompts. Every external action is a human-approved draft that the owner copies out by hand. | E8: Client services | F8: Web dashboard | G8: FastAPI, HTMX, Jinja, SQLite | H8: Windows desktop | I8: DCC tab | J8: Client services | K8: Commercial | L8: Medium | M8: Medium | N8: Weekly community operating kit. | O8: https://github.com/snknitin/community-ops-agency | Q8: 0 blocking · 2 questions · 0 proposals
A9: customer-support-agency | B9: Greenfield · host | C9: absorbs support-faq-builder, google-review-reply-desk | D9: Local-first analysis app: import a de-identified ticket export plus policy docs, cluster recurring issues, and draft policy-grounded macros, FAQs, an escalation tree, and a quality rubric — all human-reviewed and exported as an operations pack. It helps an operator design support, never run it. It also hosts two merged feature tabs: **FAQ program** (gap-ranked FAQ coverage, evidence-gap queue, help-center Markdown export, from `support-faq-builder`) and **Review replies** (manual-post public review replies grounded in the same approved policy evidence, from `google-review-reply-desk`). | E9: Client services | F9: Web dashboard | G9: Streamlit, FastAPI, sentence-transformers, Polars, Playwright, SQLite, React | H9: Windows desktop | I9: DCC tab | J9: Client services | K9: Commercial | L9: Medium | M9: High | N9: Support-design ops pack for small businesses. | O9: https://github.com/snknitin/customer-support-agency | Q9: 0 blocking · 3 questions · 0 proposals
A10: event-ops-agency | B10: Greenfield · host | C10: absorbs ai-event-matchmaker | D10: A local Next.js app that turns an event brief plus working spreadsheets (CSV) into a deadline-aware operations pack: tasks, schedule-conflict checks, run-of-show, host script, speaker cards, sponsor matrix, and reviewable message drafts. Serves one organizer running one event at a time. It also hosts the merged **Matchmaking** feature (from `ai-event-matchmaker`): a consent-controlled, auto-expiring "meet these people" queue for the same event's attendees, scored deterministically with published weights. | E10: Client services | F10: Web dashboard (Next.js) | G10: SvelteKit, Next.js, sentence-transformers, Playwright, SQLite, React | H10: Windows desktop | I10: DCC tab | J10: Client services | K10: Commercial | L10: Medium | M10: Medium | N10: Event ops + matchmaking for organizers. | O10: https://github.com/snknitin/event-ops-agency | Q10: 1 blocking · 1 questions · 0 proposals
A11: google-review-reply-desk | B11: Merged → feature | C11: customer-support-agency | E11: Client services | F11: — | G11: — | H11: — | I11: Feature of host | J11: Client services | K11: — | L11: — | M11: — | N11: Public review replies tab. | O11: https://github.com/snknitin/google-review-reply-desk | Q11: —
A12: knowledge-base-agency | B12: Greenfield | D12: A local pipeline + web app that turns a client's supplied documents into a citation-first knowledge base: parsed sources with QA, hybrid search, cited answers that abstain without evidence, a golden-question evaluation harness, and a repeatable delivery package with refresh instructions. Serves a solo operator delivering KBs to clients. | E12: Client services | F12: Web dashboard | G12: FastAPI, HTMX, Jinja, sentence-transformers, SQLite | H12: Windows desktop | I12: DCC tab | J12: Client services | K12: Commercial | L12: Medium | M12: High | N12: Kept separate by your choice; citation-first KB delivery for clients. | O12: https://github.com/snknitin/knowledge-base-agency | Q12: 0 blocking · 2 questions · 0 proposals
A13: meta-ad-creative-studio | B13: Greenfield · host | C13: absorbs paid-ad-account-audit | D13: A local creative workbench that turns one product's evidence, audience, offer, and brand system into intentionally different Meta ad concepts, renders placement-ready creative packs, and joins imported results back to the hypothesis that produced each asset. It makes disciplined creative testing cheap — it does not predict winners. It also hosts the merged **Audit** tab (from `paid-ad-account-audit`): ten deterministic audit rules over imported Google/Meta CSV exports whose accepted findings feed the studio's hypotheses and whose imported rows feed the results join. | E13: Client services | F13: Web dashboard (SvelteKit) | G13: SvelteKit, Next.js, FastAPI, Polars, DuckDB, Playwright, FFmpeg, SQLite, React | H13: Windows desktop | I13: DCC tab | J13: Client services | K13: Commercial | L13: Low | M13: High | N13: Ads audit + creative testing studio for small advertisers. | O13: https://github.com/snknitin/meta-ad-creative-studio | Q13: 0 blocking · 3 questions · 0 proposals
A14: paid-ad-account-audit | B14: Merged → feature | C14: meta-ad-creative-studio | E14: Client services | F14: — | G14: — | H14: — | I14: Feature of host | J14: Client services | K14: — | L14: — | M14: — | N14: Audit tab. | O14: https://github.com/snknitin/paid-ad-account-audit | Q14: —
A15: support-faq-builder | B15: Merged → feature | C15: customer-support-agency | E15: Client services | F15: — | G15: — | H15: — | I15: Feature of host | J15: Client services | K15: — | L15: — | M15: — | N15: Deduplicated into the support pipeline. | O15: https://github.com/snknitin/support-faq-builder | Q15: —
A16: agents-board | B16: Brownfield (live) | D16: One place to plan, start and check overnight agent work across Claude Code, Codex and Hermes. | E16: Dev | F16: Web dashboard | G16: — | H16: Windows desktop | I16: DCC tab | J16: Dev | K16: Personal | L16: Medium | M16: Low | N16: Your overnight agent board (DCC Nightly tab). | O16: https://github.com/snknitin/agents-board | Q16: —
A17: dies-at-user-50 | B17: Greenfield | D17: An authorized synthetic-user gauntlet: ramp k6 HTTP load plus a Playwright browser journey against localhost (or an ownership-verified host) until explicit latency/error thresholds break, then report the first failing stage with evidence, a bottleneck diagnosis, and a playful death certificate. The artifact is the diagnosis, not a leaderboard. | E17: Dev | F17: CLI (k6 + Playwright) | G17: Next.js, Playwright, k6 | H17: Windows / Spark | I17: CLI | J17: Dev | K17: Open-source | L17: High | M17: Medium | N17: Playful load-test 'death certificate' is a shareable dev tool. | O17: https://github.com/snknitin/dies-at-user-50 | Q17: 0 blocking · 1 questions · 0 proposals
A18: maintainer-desk | B18: Greenfield · host | C18: absorbs pr-factory | D18: A supervised operations desk for one GitHub repository: it ingests issues/PRs read-only, builds triage proposal cards (duplicates, missing info, labels, draft replies), reproduces bugs in disposable containers, and drafts PR reviews/patches — with every GitHub mutation gated behind an explicit maintainer approval record. V0 runs entirely against a local fixture repo and stops before any GitHub write. It absorbs PR Factory as the **Tournament** feature: when the maintainer asks the desk for a code patch, two isolated candidate agents race in Docker-backed worktrees against human-approved acceptance tests, deterministic QA scores them, and a deterministic judge picks one patch with its full decision trail — stopping before push or merge. | E18: Dev | F18: Web dashboard | G18: SvelteKit, FastAPI, SQLite, Docker | H18: Windows desktop / Spark | I18: DCC tab | J18: Dev | K18: Open-source | L18: High | M18: Medium | N18: Supervised OSS-maintainer desk; resonates with open-source maintainers. | O18: https://github.com/snknitin/maintainer-desk | Q18: 1 blocking · 2 questions · 0 proposals
A19: on-call-autopilot | B19: Greenfield | D19: A supervised incident investigator that replays a frozen telemetry bundle from a synthetic broken deploy, builds an evidence-backed timeline, ranks hypotheses with cited event IDs, patches a fixture in an isolated worktree, verifies locally, and emits a mock PR + postmortem for human approval. Serves an on-call engineer practicing against replay fixtures. | E19: Dev | F19: CLI + web | G19: SvelteKit, FastAPI, DuckDB, SQLite, Docker | H19: Windows / Spark | I19: DCC tab | J19: Dev | K19: Open-source | L19: High | M19: Medium | N19: Incident-practice trainer. | O19: https://github.com/snknitin/on-call-autopilot | Q19: 0 blocking · 1 questions · 0 proposals
A20: pr-factory | B20: Merged → feature | C20: maintainer-desk | E20: Dev | F20: — | G20: — | H20: — | I20: Feature of host | J20: Dev | K20: — | L20: — | M20: — | N20: Patch-tournament engine. | O20: https://github.com/snknitin/pr-factory | Q20: —
A21: adaptive-vision-glasses | B21: Greenfield | D21: A phone-based electronic magnifier for specific near/far tasks (reading labels, whiteboards, menus): zoom with autofocus lock, freeze frame, contrast profiles, OCR with reflowed large text, and text-to-speech — prioritizing low latency, readable contrast, and privacy. It is an assistive magnifier, not glasses hardware. | E21: Devices | F21: Android app | G21: Kotlin/Compose, PyTorch | H21: Phone | I21: Phone app | J21: — | K21: Open-source (assistive) | L21: High | M21: Low | N21: Assistive magnifier; open source helps people who need it. | O21: https://github.com/snknitin/adaptive-vision-glasses | Q21: 1 blocking · 2 questions · 0 proposals
A22: any-app-widget-maker | B22: Greenfield | D22: A user-configured widget builder: pick a permitted data source, map a small piece of it through simple formatting rules, and get a glanceable home-screen widget with deep-link buttons — honest about what closed apps expose ("any app" is a direction, not a guarantee). MVP is Android-first with three source types, four layouts, read-only data. | E22: Devices | F22: Android app | G22: Kotlin/Compose | H22: Phone | I22: Phone app | J22: — | K22: Commercial | L22: Medium | M22: Medium | N22: Widget builders sell on the Play Store. | O22: https://github.com/snknitin/any-app-widget-maker | Q22: 0 blocking · 2 questions · 0 proposals
A23: ar-scale-lens | B23: Greenfield | D23: An Android ARCore camera tool that makes an abstract measurement feel physical: type "91 cm" or "2,000 sq ft" and walk around a correctly scaled line, rectangle, or known-size reference object placed on the floor, then export an annotated photo. Every result carries device capability, tracking quality, and an error band — approximate by design. | E23: Devices | F23: Android app (ARCore) | G23: Kotlin/Compose, ARCore | H23: Phone | I23: Phone app | J23: — | K23: Open-source | L23: Medium | M23: Medium | N23: Scale-visualization niche. | O23: https://github.com/snknitin/ar-scale-lens | Q23: 1 blocking · 1 questions · 0 proposals
A24: drone-mission-mapper | B24: Greenfield | D24: Simulation-first mission planner: draw a survey area on a map, generate a safe flight pattern with battery/coverage estimates, validate it, fly it in SITL only, then georeference captured frames and run text-prompted object detection whose hits require human confirmation. No physical takeoff anywhere in this build. | E24: Devices | F24: Web + SITL | G24: Tauri, FastAPI, SQLite, React | H24: Windows (WSL2) / Linux | I24: Standalone web | J24: Labs | K24: Open-source | L24: High | M24: Medium | N24: Simulation-first mission planning. | O24: https://github.com/snknitin/drone-mission-mapper | Q24: 0 blocking · 2 questions · 0 proposals
A25: field-pokedex | B25: Greenfield | D25: An Expo mobile app that identifies likely plant species from a photo via a hosted identification API, shows ranked candidates with confidence and lookalikes, pulls attributed taxonomy/facts, and saves confirmed-or-unresolved observations into a private collectible journal. Serves one naturalist in one region. | E25: Devices | F25: Phone app (Expo) | G25: Expo, SQLite, React | H25: Phone | I25: Phone app | J25: — | K25: Personal → Commercial | L25: Medium | M25: Medium | N25: Collectible plant journal. | O25: https://github.com/snknitin/field-pokedex | Q25: 0 blocking · 2 questions · 0 proposals
A26: 27-clicks-to-cancel | B26: Merged → feature | C26: paisa-vasool-subscriptions | E26: Finance | F26: — | G26: — | H26: — | I26: Feature of host | J26: Money | K26: — | L26: — | M26: — | N26: Cancel-assist step inside Paisa. | O26: https://github.com/snknitin/27-clicks-to-cancel | Q26: —
A27: edge-desk | B27: Merged → feature | C27: event-market-research-terminal | E27: Finance | F27: — | G27: — | H27: — | I27: Feature of host | J27: Money | K27: — | L27: — | M27: — | N27: Its alerts and ambiguity warnings now live in EMRT. | O27: https://github.com/snknitin/edge-desk | Q27: —
A28: event-market-research-terminal | B28: Greenfield · host | C28: absorbs edge-desk | D28: A research-only terminal for event markets and crypto narratives: for each manually-watched market it freezes timestamped evidence dossiers (resolution rules, price/liquidity/spread, catalysts, primary sources, counterarguments, narrative shifts, falsifiers), logs paper decisions before outcomes, and scores calibration later. Anti-hype by design: base rate, liquidity, time-to-resolution, and the strongest disconfirming evidence always render before sentiment. Merged feature: **Edge Desk** adds liquidity-gated market-move alerts, resolution-rule versioning with ambiguity warnings, paper positions, and baseline replay as a "Moves & rules" tab. | E28: Finance | F28: Web dashboard (Streamlit) | G28: Streamlit, FastAPI, n8n, Polars, DuckDB, SQLite | H28: Windows desktop | I28: DCC tab | J28: Money | K28: Personal → Open-source | L28: Medium | M28: Medium | N28: Research-only calibration workspace; a commercial route exists but compliance/overconfidence costs are high. | O28: https://github.com/snknitin/event-market-research-terminal | Q28: 1 blocking · 2 questions · 1 proposals
A29: finance-ops-agency | B29: Greenfield · host | C29: absorbs invoice-chaser-agent, tax-packet-autopilot | D29: A local finance-operations desk for a freelancer: imports invoice/expense/bank/reimbursement exports, proposes payment↔invoice matches, routes uncertainty to a review queue, and produces receivable aging, a payable calendar, three-scenario cash view, and a review-ready monthly close memo with an evidence manifest. Merged features: **Invoice Chaser** adds a Receivables → Chase tab that drafts tone-escalating reminders from the same imports (every reminder still needs a click; nothing is sent by the app), and **Tax Packet** adds a "Tax packet for CA" tab that turns imported invoices/receipts into a reviewed, deduplicated GST evidence packet. | E29: Finance | F29: Web dashboard | G29: Streamlit, FastAPI, Jinja, Polars, DuckDB, SQLite | H29: Windows desktop | I29: DCC tab | J29: Money | K29: Commercial | L29: Medium | M29: High | N29: Freelancer AR + monthly close + CA tax packet is a sellable bundle, especially for Indian freelancers and their CAs. | O29: https://github.com/snknitin/finance-ops-agency | Q29: 1 blocking · 2 questions · 1 proposals
A30: finance-signals-dashboard | B30: Greenfield · host | C30: absorbs market-mood-cards | D30: A read-only, local-first personal dashboard that ranks a ten-instrument India/US watchlist by "research priority" (which instrument deserves the next unit of investigation), with every rank fully reproducible from stored formulas, raw-data hashes, and human-approved signal policies. Serves exactly one user on one Windows machine and appears in Dashboard Command Center's Finance group, which `personal-finance-cockpit` composes. Merged feature: **Morning mood** (formerly the standalone `market-mood-cards`) adds a Morning tab. At 08:15 IST it publishes one calm, immutable issue: exact completed-session moves for six named indices, one BTC/USD display observation, deduplicated headlines and a template summary. It is built on this app's instruments, ingestion, raw store, lease/receipts, scheduler and SQLite. | E30: Finance | F30: Web dashboard (SvelteKit) | G30: SvelteKit, FastAPI, Jinja, Playwright, SQLite | H30: Windows desktop | I30: DCC tab | J30: Money | K30: Personal | L30: Medium | M30: Low | N30: Market-data licences block redistribution; could open-source as a bring-your-own-data engine. | O30: https://github.com/snknitin/finance-signals-dashboard | Q30: 1 blocking · 9 questions · 2 proposals
A31: invoice-chaser-agent | B31: Merged → feature | C31: finance-ops-agency | E31: Finance | F31: — | G31: — | H31: — | I31: Feature of host | J31: Money | K31: — | L31: — | M31: — | N31: Receivables/chase tab inside Finance Ops. | O31: https://github.com/snknitin/invoice-chaser-agent | Q31: —
A32: latte-into-lambo | B32: Merged → feature | C32: net-worth-command-center | E32: Finance | F32: — | G32: — | H32: — | I32: Feature of host | J32: Money | K32: — | L32: — | M32: — | N32: Now Net Worth's What-if tab. | O32: https://github.com/snknitin/latte-into-lambo | Q32: —
A33: market-mood-cards | B33: Merged → feature | C33: finance-signals-dashboard | D33: A standalone, Spark-hosted morning-briefing pipeline and private dashboard: at a configured cutoff it publishes one immutable "issue" with exact completed-session moves for six named equity indices (NIFTY 50, S&P 500, Nikkei 225, KOSPI, STI, CSI 300) plus BTC/USD spot, deduplicated regional headlines, a deterministic template summary, and full evidence provenance. Serves one user via tailnet through Dashboard Command Center. | E33: Finance | F33: — | G33: FastAPI, Jinja, SQLite | H33: — | I33: Feature of host | J33: Money | K33: — | L33: — | M33: — | N33: Morning tab of Finance Signals. | O33: https://github.com/snknitin/market-mood-cards | Q33: —
A34: net-worth-command-center | B34: Greenfield · host | C34: absorbs latte-into-lambo | D34: A private, local-first personal-finance record for one person: import statements/balances, reconcile them against evidence, and produce locked month-end USD snapshots with known/estimated/excluded totals — all deterministic, with no model authority over money. Serves the single owner on one Windows machine, registered as a Money module in Dashboard Command Center by URL/health only. Merged feature: **What-if** (formerly the standalone `latte-into-lambo`) adds a counterfactual tab that replays the user's reviewed spend against frozen price/FX/CPI data releases through a pure, fingerprinted calculation kernel, reading Net Worth's own committed transactions in-process. | E34: Finance | F34: Web dashboard | G34: FastAPI, Jinja, SQLite | H34: Windows desktop | I34: DCC tab | J34: Money | K34: Personal | L34: Low | M34: Low | N34: Private balance-sheet record. Its value is trust in your own numbers, not distribution. | O34: https://github.com/snknitin/net-worth-command-center | Q34: 2 blocking · 5 questions · 2 proposals
A35: paisa-vasool-subscriptions | B35: Greenfield · host | C35: absorbs renewal-guard, 27-clicks-to-cancel | D35: A private, local-first subscription-utilization tracker for one user: it discovers recurring charges from years of transaction history (via a read-only Net Worth view or manual registry), explains which optional subscriptions are underused, prepares reviewed cancellation/downgrade/use-better actions, and counts savings only after a later statement proves the charge stopped. Merged features: **Renewal Guard** makes receipts/invoices/warranties Paisa's second evidence source with a Renewals & warranties tab, and **Cancel Assist** (from 27-clicks-to-cancel) executes an approved cancellation packet in a supervised browser with a page-state-bound human-approval hard stop before the final click. | E35: Finance | F35: Web dashboard | G35: SvelteKit, FastAPI, Jinja, Playwright, SQLite | H35: Windows desktop | I35: DCC tab | J35: Money | K35: Personal → Commercial | L35: Medium | M35: Medium | N35: Verified cancellations + utilization is a real consumer pain; local-first privacy is the differentiator. | O35: https://github.com/snknitin/paisa-vasool-subscriptions | Q35: 1 blocking · 4 questions · 3 proposals
A36: personal-finance-cockpit | B36: Greenfield | D36: The **Finance group inside Dashboard Command Center (DCC)** — not a standalone app (owner decision 2026-10-20). DCC already owns navigation, windows, sessions, endpoint health probes and display; each finance module owns its own data, rules, actions and UI. This project owns only what neither does: 1. **Composition** — which finance modules register in DCC's Finance group, in what order, with which endpoints, health URLs, session boundaries and activation state: Balance Sheet (`net-worth-command-center`), Subscriptions (`paisa-vasool-subscriptions`), Market Signals (`finance-signals-dashboard`), Crypto & Event Markets (`event-market-research-terminal`). It emits DCC registry records; the owner imports them through DCC's existing **Import registry**. 2. **A thin loopback aggregator** registered as the group's first dashboard, *Finance Overview*: the cross-module provenance/health board (source time, version, freshness, backup state per module), the digest preview and the export index — on one read-only page, plus a DCC capability manifest carrying a one-line group status. 3. **One finance notification policy** (triggers, previews, quiet hours, one digest). | E36: Finance | F36: DCC Finance group + overview page | G36: FastAPI, Jinja, SQLite | H36: Windows desktop | I36: DCC group | J36: Money | K36: Personal | L36: Low | M36: Low | N36: Composition layer only: groups the finance apps inside Dashboard Command Center. | O36: https://github.com/snknitin/personal-finance-cockpit | Q36: 1 blocking · 1 questions · 3 proposals
A37: renewal-guard | B37: Merged → feature | C37: paisa-vasool-subscriptions | E37: Finance | F37: — | G37: — | H37: — | I37: Feature of host | J37: Money | K37: — | L37: — | M37: — | N37: Receipts/warranties tab inside Paisa. | O37: https://github.com/snknitin/renewal-guard | Q37: —
A38: tax-packet-autopilot | B38: Merged → feature | C38: finance-ops-agency | E38: Finance | F38: — | G38: — | H38: — | I38: Feature of host | J38: Money | K38: — | L38: — | M38: — | N38: Tax-packet-for-CA tab inside Finance Ops. | O38: https://github.com/snknitin/tax-packet-autopilot | Q38: —
A39: live-chess-tutor | B39: Greenfield | D39: A local desktop chess board for guided practice: during unrated games against embedded Stockfish (or positions from personal PGNs), it spots teachable moments before the move is committed, asks the learner to reason ("checks, captures, threats?"), reveals hints progressively, and logs concept mastery for spaced review. Pedagogy and timing are the product; the engine analysis is commodity. | E39: Games | F39: Desktop app | G39: Tauri, SQLite | H39: Windows desktop | I39: Standalone desktop | J39: — | K39: Open-source | L39: High | M39: Medium | N39: Pedagogy-first chess tutor. | O39: https://github.com/snknitin/live-chess-tutor | Q39: 0 blocking · 0 questions · 0 proposals
A40: murder-mystery-game-master | B40: Greenfield | D40: A deterministic party-game engine for 45–90 minute murder mysteries on a local LAN: it privately assigns fictional roles, releases timed clues, collects theories and one vote, and narrates a reveal — with AI adding bounded flavor while an append-only event log keeps state consistent and replayable. Works for a six-player party and as a single-player mental exercise (the engine reveals the solution if nobody pieces it together). | E40: Games | F40: LAN party web app | G40: Next.js, SQLite | H40: Windows desktop + LAN | I40: Party / LAN app | J40: — | K40: Commercial | L40: Medium | M40: Medium | N40: Party-game kits sell; AI-bounded narration is a hook. | O40: https://github.com/snknitin/murder-mystery-game-master | Q40: 0 blocking · 2 questions · 2 proposals
A41: rabbit-hole-speedrun | B41: Merged → feature | C41: expert-lens-skill | D41: A local single-player knowledge game: start from a topic, hop six steps through surprising but source-backed Wikipedia/Wikidata connections (three choices per step), against a timer, ending in a shareable path card with facts and citations. The model never invents links — it only explains edges retrieved and validated from sources. | E41: Games | F41: — | G41: Next.js, SQLite | H41: — | I41: Feature of host | J41: Learning | K41: — | L41: — | M41: — | N41: Speedrun tab of Expert Lens. | O41: https://github.com/snknitin/rabbit-hole-speedrun | Q41: —
A42: dashboard-command-center | B42: Brownfield (live) | D42: A Windows operations shell that organizes private dashboards as workbook-style tabs and groups. | E42: Hub | F42: Desktop shell (Electron) | G42: Electron, TypeScript | H42: Windows desktop | I42: The hub itself | J42: — | K42: Personal → Open-source | L42: High | M42: Medium | N42: The hub every DCC tab lives in. | O42: https://github.com/snknitin/dashboard-command-center | Q42: —
A43: audio-watermark-and-perception-lab | B43: Greenfield | D43: A transparent local laboratory: embed a declared AudioSeal watermark (optional small payload) into the owner's audio, run a frozen attack matrix, measure detector behavior (TP/FP, localization, payload recovery, robustness curves), run loudness-matched ABX listening sessions, and compare everything against a signed-sidecar provenance baseline — showing what each mechanism can and cannot prove. | E43: Labs | F43: CLI lab | G43: Streamlit, PyTorch, FFmpeg, SQLite | H43: Windows desktop | I43: Lab harness | J43: Labs | K43: Open-source | L43: High | M43: Low | N43: Transparent watermark robustness lab. | O43: https://github.com/snknitin/audio-watermark-and-perception-lab | Q43: 0 blocking · 1 questions · 0 proposals
A44: local-video-generation-evaluation-lab | B44: Greenfield | D44: A reproducible CLI benchmark harness answering one question: which exact video-generation configuration (model revision × runtime × precision × attention × offload × resolution/frames/steps/seed × machine) produces an acceptable clip for a specific creator task at acceptable latency, memory, setup burden, and cost. Results are task- and machine-scoped, never a universal leaderboard. | E44: Labs | F44: CLI benchmark harness | G44: ComfyUI, FFmpeg, SQLite | H44: Windows (48 GB GPU) / Spark | I44: Lab harness | J44: Labs | K44: Open-source | L44: High | M44: Low | N44: Reproducible benchmark results are valuable as open research. | O44: https://github.com/snknitin/local-video-generation-evaluation-lab | Q44: 2 blocking · 1 questions · 1 proposals
A45: marionettist-utopia | B45: Greenfield | D45: A private synthetic-society sandbox: 6–12 clearly fictional original characters develop interests, relationships, memories, and conversations over daily simulation ticks, rendered as a local social feed where every action is explainable from visible state. The engine separates deterministic *intent* selection from model-rendered *utterance*. | E45: Labs | F45: Web app (SvelteKit) + FastAPI | G45: SvelteKit, FastAPI, SQLite | H45: Windows desktop | I45: Standalone web | J45: Labs | K45: Open-source | L45: High | M45: Medium | N45: Explainable NPC/society engine for games and writers. | O45: https://github.com/snknitin/marionettist-utopia | Q45: 1 blocking · 1 questions · 0 proposals
A46: tiny-model-game-lab | B46: Greenfield | D46: A reproducible local research lab that measures where capability comes from when a 135M–270M model plays Wordle: prompting vs constraints vs tools vs teacher distillation, always against deterministic classical ceilings on a pinned lexicon. Serves the owner's research question "where does capability actually come from when parameters are scarce?", with honest capability accounting per variant. | E46: Labs | F46: CLI research lab | G46: PyTorch, Gymnasium | H46: Windows / Spark | I46: Lab harness | J46: Labs | K46: Open-source | L46: High | M46: Low | N46: Where small-model capability comes from: open research. | O46: https://github.com/snknitin/tiny-model-game-lab | Q46: 2 blocking · 1 questions · 0 proposals
A47: visual-token-compiler | B47: Greenfield | D47: A local benchmark-driven compiler: take structured source content and a task, compile it into several encodings (compact text/JSON, SVG card, raster), run the same fixed questions against a target multimodal model, and report the cost–accuracy–latency Pareto frontier with a source map from every rendered region back to the original data. Serves the owner deciding when "a picture is worth a thousand tokens" is actually true for a given model. | E47: Labs | F47: CLI benchmark | G47: Playwright, SQLite | H47: Windows / Spark | I47: Lab harness | J47: Labs | K47: Open-source | L47: High | M47: Low | N47: Encoding-vs-accuracy research. | O47: https://github.com/snknitin/visual-token-compiler | Q47: 0 blocking · 0 questions · 0 proposals
A48: yugioh-rl-lab | B48: Greenfield | D48: A reproducible card-battler RL laboratory built on an original small rules engine (40–100 cards, hidden information), with Gymnasium interfaces, impossible-by-construction illegal actions, deterministic replay, scripted baselines, and one neural RL baseline evaluated against frozen opponents. The point is learning RL environment design correctly. | E48: Labs | F48: Gymnasium RL lab | G48: Streamlit, Gradio, Polars, PyTorch, Gymnasium | H48: Windows / Spark | I48: Lab harness | J48: Labs | K48: Open-source | L48: High | M48: Low | N48: Original rules engine for RL learning. | O48: https://github.com/snknitin/yugioh-rl-lab | Q48: 1 blocking · 0 questions · 0 proposals
A49: course-notes-to-quiz-product | B49: Merged → feature | C49: personal-study-curriculum | E49: Learning | F49: — | G49: — | H49: — | I49: Feature of host | J49: Learning | K49: — | L49: — | M49: — | N49: Notes → cards importer inside the curriculum. | O49: https://github.com/snknitin/course-notes-to-quiz-product | Q49: —
A50: expert-lens-skill | B50: Greenfield · host | C50: absorbs batman-prep-time-skill, goal-to-calendar-planner, rabbit-hole-speedrun | D50: **Expert Lens** (repo `expert-lens-skill`) is one private FirstSpark dashboard service. It turns "domain + situation + counterpart + outcome" into an evidence-backed **field card** (topology, vocabulary ladder with paraphrase tests, mechanism map, ranked expert questions, distinctions, rehearsal), and keeps every topic as a Markdown workspace you can read, edit and chat with through the owner's GLM 5.3 model. Merged features: **Batman Prep** (prep for any commitment, with Goal-to-Calendar planning as its approval-gated scheduling step) and **Rabbit Hole Speedrun** (a source-backed knowledge game that can start from a library topic). The Markdown library on disk is the source of truth and SQLite is a rebuildable index. It is deployed like YouTube Learning Center (YLC): a systemd user unit on `127.0.0.1:8767`, published at `https://spark-07a8.tail4a1242.ts.net:8767/` with Tailscale Serve, and shown as a tab in Dashboard Command Center (DCC). | E50: Learning | F50: Spark dashboard | G50: Next.js, FastAPI, OR-Tools, sentence-transformers, Playwright, DSPy, SQLite, React | H50: FirstSpark (systemd, :8767) | I50: Skill | J50: Learning | K50: Personal → Open-source | L50: High | M50: Medium | N50: One FirstSpark dashboard: field cards, Batman Prep with approval-gated planning, Speedrun; Markdown library + GLM chat. | O50: https://github.com/snknitin/expert-lens-skill | Q50: 1 blocking · 9 questions · 1 proposals
A51: half-blood-pdf | B51: Built elsewhere | D51: A local pipeline that enriches a text-based PDF with reviewed marginal annotations (clarifications, corrections, prerequisites, questions, analogies, diagrams) rendered as a new PDF, while the canonical project stays an editable manifest and the source file is never touched. Serves the owner's own study of dense chapters/papers. | E51: Learning | F51: Hosted web app | G51: Tauri, SQLite, React | H51: Cloudflare | I51: Hosted product | J51: — | K51: Commercial (live) | L51: Low | M51: High | N51: Complete and live on Cloudflare with a paywall. | O51: https://github.com/snknitin/half-blood-pdf | Q51: —
A52: handwriting-to-latex | B52: Greenfield | D52: A local desktop hotkey utility: drag around one isolated handwritten/printed equation, get LaTeX from a local pix2tex model, see it rendered beside the crop, fix ambiguous tokens faster than retyping, and copy the result (bare or wrapped) to the clipboard for Overleaf/Markdown. | E52: Learning | F52: Desktop hotkey app (Qt) | G52: Tauri, PyTorch, SQLite, Qt | H52: Windows desktop | I52: Standalone desktop | J52: — | K52: Open-source | L52: High | M52: Medium | N52: Local equation-to-LaTeX utility; students and researchers would adopt an open-source version. | O52: https://github.com/snknitin/handwriting-to-latex | Q52: 0 blocking · 2 questions · 0 proposals
A53: kaggle-learning-center | B53: Brownfield (live) | D53: A Kaggle learning studio: radar of what's new, solved-competition case studies, and an interview drill. | E53: Learning | F53: Web dashboard | G53: — | H53: FirstSpark | I53: DCC tab | J53: Learning | K53: Personal | L53: Low | M53: Low | N53: Kaggle radar, case studies and drills. | O53: https://github.com/snknitin/kaggle-learning-center | Q53: —
A54: language-learning-lab | B54: Greenfield · host | C54: absorbs vocabulary-diction-studio | D54: A local-first language workbench organised by **language tracks** over one shared core: lexeme/sense/card store, one FSRS scheduler, idempotent attempts, a day-wide admission ledger, audio capture/analysis, STT/TTS/LLM adapters, durable jobs, backups and one Expo UI (native + web). **English** is the first-class track and carries everything Vocabulary & Diction Studio specified: the owner's Google Sheet → context-to-word reverse recall, Handy (Parakeet) dictations → evidence-linked diction coaching and a ten-minute drill, selected Markdown exports. Every other language is a config-defined track running the lab's three loops (frequency-informed learning, FSRS recall, speaking with interpretable A/B + timing/pitch feedback — never an accent score). Merged feature: `vocabulary-diction-studio` → the English track (`F-en-*`). The app runs on the Windows workstation as the single writer and is a **Dashboard Command Center** tab in group **Learning**. | E54: Learning | F54: Phone app (Expo) + FastAPI | G54: Expo, FastAPI, SQLite, React | H54: Windows desktop (+ phone via Tailscale) | I54: Phone app | J54: Learning | K54: Personal → Commercial | L54: Medium | M54: Medium | N54: README: one excellent pronunciation module is more defensible than a Duolingo clone. | O54: https://github.com/snknitin/language-learning-lab | Q54: 5 blocking · 2 questions · 0 proposals
A55: leetcode-pattern-curriculum | B55: Greenfield | D55: A local, Python-only algorithms curriculum: user-authored pattern modules (Markdown/YAML) that teach recognition → invariant → implementation → transfer, with a local pytest/Hypothesis runner, a four-level hint ladder, attempt telemetry, and FSRS-scheduled reviews. External problems are linked, never copied; solution authors are credited per license. | E55: Learning | F55: CLI + Obsidian | G55: SQLite | H55: Windows / Spark | I55: CLI + Obsidian | J55: Learning | K55: Open-source | L55: High | M55: Low | N55: User-authored pattern modules + local runner fit the open-source study community. | O55: https://github.com/snknitin/leetcode-pattern-curriculum | Q55: 1 blocking · 1 questions · 0 proposals
A56: longvid-learning-studio | B56: Retired (archived) | C56: youtube-learning-center | D56: The earlier version of YouTube Learning Center. | E56: Learning | F56: — | G56: — | H56: — | I56: Archived | J56: — | K56: — | L56: — | M56: — | N56: Older version of YouTube Learning Center. | O56: https://github.com/snknitin/longvid-learning-studio | Q56: —
A57: personal-study-curriculum | B57: Greenfield · host | C57: absorbs course-notes-to-quiz-product | D57: A local-first tool that turns one learning goal, weekly hours, and manually imported resources into a dependency-aware two-week sprint with retrieval practice, evidence-gated mastery, and a weekly review that proposes plan changes for approval. It answers "what should I learn next, why, and how do I prove it." It is also the downstream owner of learning plans for skill gaps proposed by Jobs Search and Apply Tool and Mock Interview Gauntlet (`career.study-gaps.v1`), which land only as proposals. It absorbs Course Notes to Quiz Product as the **Notes** feature: pasted notes become source-linked, validated cards that feed the curriculum's own FSRS queue. | E57: Learning | F57: Web dashboard (Next.js) | G57: Next.js, FastAPI, HTMX, Jinja, n8n, sentence-transformers, SQLite, React, Docker | H57: Windows desktop | I57: DCC tab | J57: Learning | K57: Personal → Open-source | L57: High | M57: Medium | N57: README's product path is open-source 'curriculum as code'. | O57: https://github.com/snknitin/personal-study-curriculum | Q57: 2 blocking · 3 questions · 1 proposals
A58: physics-claim-debunker-skill | B58: Greenfield | D58: A local research skill that turns an extraordinary claim into measurable subclaims, steelmans it, tests it with conservation laws, dimensions, orders of magnitude, geometry, and statistics via deterministic unit-aware code, compares predictions with primary measurements, and renders a layered (beginner/intermediate/technical) report with one of six verdict categories — including "unresolved" and "unfalsifiable as phrased". Value is the visible reasoning path, not a dramatic debunk. | E58: Learning | F58: Skill + CLI | G58: — | H58: Claude Code / Codex / Hermes | I58: Skill | J58: — | K58: Open-source | L58: Medium | M58: Low | N58: Deterministic, unit-aware claim checks: good open-source education. | O58: https://github.com/snknitin/physics-claim-debunker-skill | Q58: 0 blocking · 1 questions · 0 proposals
A59: taxonomy-cluster-explorer | B59: Greenfield | D59: A local-first dual-view explorer: the authoritative biological taxonomy (versioned snapshot) on one side, an experimental hierarchical-agglomerative-clustering dendrogram of the same taxa on the other, with linked highlighting and merge explanations. Serves one learner studying how similarity clustering agrees/disagrees with accepted classification. | E59: Learning | F59: Web app | G59: SvelteKit, Polars, DuckDB, React | H59: Windows desktop | I59: Standalone web | J59: Learning | K59: Open-source | L59: Medium | M59: Low | N59: Educational dual-view explorer. | O59: https://github.com/snknitin/taxonomy-cluster-explorer | Q59: 0 blocking · 2 questions · 0 proposals
A60: tiktok-learning-center | B60: Brownfield (live) | D60: Turns a private TikTok collection into one cited Markdown learning package. | E60: Learning | F60: Web dashboard (React) | G60: FastAPI, SQLite, React | H60: FirstSpark | I60: DCC tab | J60: Learning | K60: Personal | L60: Low | M60: Low | N60: TikTok collections into learning packages. | O60: https://github.com/snknitin/tiktok-learning-center | Q60: —
A61: understand-this-paper | B61: Built elsewhere | D61: An interactive research-paper tutor for ML arXiv papers: import an arXiv ID or PDF, get an orientation summary, a symbol table, color-coded equations, one step-by-step equation walkthrough, executable pseudocode, and citation anchors that jump back to the exact source region. Serves the owner reading ML papers; differentiator vs NotebookLM is the equation/symbol dependency viewer + executable pseudocode, not general PDF chat. | E61: Learning | F61: Browser extension | G61: SvelteKit, Next.js, FastAPI, SQLite, React, Docker | H61: Browser | I61: Browser extension | J61: — | K61: Open-source (owner plan) | L61: High | M61: Low | N61: Almost complete hackathon build; remaining work is extension packaging + open-sourcing. | O61: https://github.com/snknitin/understand-this-paper | Q61: —
A62: vocabulary-diction-studio | B62: Merged → feature | C62: language-learning-lab | D62: A personal Windows-first workbench that turns a vocabulary Google Sheet into durable context-to-word recall (reverse recall, FSRS-scheduled) and turns selected Handy dictations into evidence-linked speech coaching with a ten-minute daily drill. Single Windows writer; private models only; Markdown exports are selected artifacts, not the learning database. | E62: Learning | F62: — | G62: FastAPI, SQLite, React | H62: — | I62: Feature of host | J62: Learning | K62: — | L62: — | M62: — | N62: English track of the Language Learning Lab. | O62: https://github.com/snknitin/vocabulary-diction-studio | Q62: —
A63: youtube-learning-center | B63: Brownfield (live) | D63: A playlist-aware learning workstation: YouTube player plus source-grounded Markdown study artifacts. | E63: Learning | F63: Web dashboard | G63: FastAPI, SQLite, React | H63: FirstSpark (systemd) | I63: DCC tab | J63: Learning | K63: Personal | L63: Medium | M63: Medium | N63: Your live playlist-learning workstation. | O63: https://github.com/snknitin/youtube-learning-center | Q63: —
A64: quiz-master | B64: Greenfield · host | C64: absorbs quiz-poker | D64: A local quiz-authoring studio that learns structural patterns from the owner's private K-Circle yearbook corpus, turns a topic/entity into clue-driven question drafts with a cited evidence ledger, lints them deterministically, and ships reviewed packs plus a Question of the Day. Merged feature: **Quiz Poker** becomes the app's **Game** tab beside the **Studio** tab — a points-only LAN game where 4–12 friends wager confidence on Studio-reviewed packs, with hashed commits and an authoritative server. `qm.pack.v1` / `qm.question.v1` (§4) is now an internal module both tabs use. | E64: Learning / games | F64: Web app (Studio + LAN Game) | G64: SvelteKit, Streamlit, FastAPI, Playwright, SQLite | H64: Windows desktop + LAN | I64: DCC tab | J64: Learning | K64: Personal | L64: Medium | M64: Low | N64: Built on a private yearbook corpus, so it stays personal; the game engine could open-source. | O64: https://github.com/snknitin/quiz-master | Q64: 1 blocking · 3 questions · 0 proposals
A65: quiz-poker | B65: Merged → feature | C65: quiz-master | E65: Learning / games | F65: — | G65: — | H65: — | I65: Feature of host | J65: Learning | K65: — | L65: — | M65: — | N65: Game tab inside Quiz Master. | O65: https://github.com/snknitin/quiz-poker | Q65: —
A66: ambient-tv | B66: Greenfield | D66: A lean-back channel guide for the owner's own Jellyfin library: deterministic playlists mapped to wall-clock time become "channels", so tuning in at 8:17 starts seventeen minutes into the current program. Guide grid, now/next, one-click surfing — the pleasure of not choosing. | E66: Media | F66: Web app for Jellyfin | G66: React | H66: Home server / LAN | I66: Standalone web | J66: — | K66: Open-source | L66: High | M66: Low | N66: Jellyfin community would love channel-style TV. | O66: https://github.com/snknitin/ambient-tv | Q66: 0 blocking · 2 questions · 0 proposals
A67: angel-and-demon-companion | B67: Kept (ideas ported) | C67: motto-agent-council | D67: Two virtual pets argue a choice from your values (half-day hackathon site). | E67: Personal ops | F67: Website (hackathon) | G67: Expo, SQLite, React | H67: — | I67: Low priority | J67: — | K67: Personal | L67: Low | M67: Low | N67: Half-day hackathon site; ideas now live in Motto Council; repo left alone. | O67: https://github.com/snknitin/angel-and-demon-companion | Q67: —
A68: batman-prep-time-skill | B68: Merged → feature | C68: expert-lens-skill | D68: A Codex/Hermes skill that turns any pasted commitment (meeting, trip, exam, purchase, deadline, difficult conversation…) into the smallest high-signal preparation pack: mission, situation map, Pareto brief, backward plan, questions, pre-mortem, contingencies, and a ten-minute card — all inside a user-selected time budget. It can also take a Jobs Search and Apply Tool `interview-prep.json` as context for an interview. | E68: Personal ops | F68: — | G68: — | H68: — | I68: Feature of host | J68: Learning | K68: — | L68: — | M68: — | N68: Batman Prep tab of Expert Lens. | O68: https://github.com/snknitin/batman-prep-time-skill | Q68: —
A69: brain-blast-skill | B69: Greenfield | D69: A Markdown skill package that turns one everyday irritation into one cheap, reversible experiment: reframe the problem, apply a deterministic deck of creativity operators, score options, and emit a single experiment card plus an outcome log entry. Serves the owner's local agent (Claude Code / Codex / Hermes-style skill invocation). | E69: Personal ops | F69: Skill | G69: — | H69: Claude Code / Codex / Hermes | I69: Skill | J69: — | K69: Open-source | L69: Medium | M69: Low | N69: Small creativity skill. | O69: https://github.com/snknitin/brain-blast-skill | Q69: 0 blocking · 3 questions · 0 proposals
A70: brainrot-rehab | B70: Merged → feature | C70: paper-logbook | E70: Personal ops | F70: — | G70: — | H70: — | I70: Feature of host | J70: — | K70: — | L70: — | M70: — | N70: Screen-time experiment pack inside Paper Logbook. | O70: https://github.com/snknitin/brainrot-rehab | Q70: —
A71: daily-parent-check-in | B71: Greenfield | D71: Consent-first local app that sends one daily check-in prompt to a parent (via a simulated inbox for V0), accepts text or voice replies, transcribes locally, extracts memories/requests, and gives the adult child an editable evening digest with explicitly configured concern signals only. Every outbound message is child-approved; the parent can pause or revoke at any time from their own page. | E71: Personal ops | F71: Web dashboard | G71: FastAPI, HTMX, Jinja, SQLite | H71: Windows desktop | I71: DCC tab | J71: Personal | K71: Personal → Commercial | L71: Low | M71: Medium | N71: Family/elder check-in market exists but is privacy-sensitive. | O71: https://github.com/snknitin/daily-parent-check-in | Q71: 1 blocking · 2 questions · 0 proposals
A72: dunbar-dossier | B72: Brownfield (live) | D72: A private biographic archive (Dunbar 150) with evidence-backed dossiers and meeting briefs. | E72: Personal ops | F72: Web workspace | G72: FastAPI, SQLite | H72: FirstSpark / Windows | I72: DCC tab | J72: Personal | K72: Personal | L72: Low | M72: Low | N72: Your private Dunbar 150 archive. Parked: pocket-crm idea note. | O72: https://github.com/snknitin/dunbar-dossier | Q72: —
A73: feedback-mirror | B73: Greenfield | D73: A privacy-first, on-device daily appearance journal: guided webcam capture under standardized pose/lighting, self-reported sleep/routine notes, and exactly two transparent non-diagnostic image measurements shown as raw-value trends with comparability warnings. Serves one person on one device. | E73: Personal ops | F73: On-device web (webcam) | G73: SQLite | H73: Windows desktop | I73: Standalone web | J73: — | K73: Personal | L73: Low | M73: Low | N73: Sensitive appearance journal; keep personal. | O73: https://github.com/snknitin/feedback-mirror | Q73: 1 blocking · 2 questions · 0 proposals
A74: goal-to-calendar-planner | B74: Merged → feature | C74: expert-lens-skill | D74: An approval-based local planner that turns one large goal into milestones and dependency-aware tasks, fits them into real free time with deliberate slack using a constraint solver, previews every week as a diff before any block exists, and replans from what actually happened — explaining every change. It is also the **owner of task/plan truth** that NPC Mode Coach and Jarvis and Alfred read (see §4 "Shared task truth"). | E74: Personal ops | F74: — | G74: Next.js, FastAPI, n8n, OR-Tools, Playwright, SQLite | H74: — | I74: Feature of host | J74: Learning | K74: — | L74: — | M74: — | N74: Plan step inside the Batman Prep tab; g2c.tasks.v1 now served by Expert Lens. | O74: https://github.com/snknitin/goal-to-calendar-planner | Q74: —
A75: inbox-zero-mercenary | B75: Greenfield | D75: A reversible email triage desk: it buckets a Gmail inbox (urgent reply, waiting, reference, newsletter, receipt, stale, uncertain), explains every placement, proposes labels/archives/unsubscribes/reply drafts, and executes only what the user approves — with a ledger that can roll back every mutation. Serves one personal Gmail account. | E75: Personal ops | F75: Web dashboard | G75: SvelteKit, FastAPI, SQLite | H75: Windows desktop | I75: DCC tab | J75: Personal | K75: Personal → Commercial | L75: Medium | M75: High | N75: Reversible, explainable email triage is a large market. | O75: https://github.com/snknitin/inbox-zero-mercenary | Q75: 1 blocking · 1 questions · 0 proposals
A76: jarvis-and-alfred | B76: Merged → feature | C76: motto-agent-council | D76: A two-role personal executive-assistant harness: Jarvis turns requests into bounded, previewed tasks and drafts; Alfred maintains the morning brief/weekly review and challenges overload. Both share one structured memory with provenance and one authority model — personality never changes authority. Calendar and task data are read from the same sources Goal-to-Calendar Planner and NPC Mode Coach use; this harness never owns task truth. | E76: Personal ops | F76: — | G76: FastAPI, HTMX, LangGraph, SQLite | H76: — | I76: Feature of host | J76: Personal | K76: — | L76: — | M76: — | N76: Jarvis and Alfred become council voices / desktop pets. | O76: https://github.com/snknitin/jarvis-and-alfred | Q76: —
A77: measure-life | B77: Merged → feature | C77: paper-logbook | E77: Personal ops | F77: — | G77: — | H77: — | I77: Feature of host | J77: — | K77: — | L77: — | M77: — | N77: Insights & experiments tab inside Paper Logbook. | O77: https://github.com/snknitin/measure-life | Q77: —
A78: motto-agent-council | B78: Greenfield · host | C78: absorbs jarvis-and-alfred, parallel-presence-companions | D78: A local council of small, explicit perspective agents — each a user-authored charter (builder, skeptic, health protector…) — that critique one decision from identical facts, label every claim as fact/assumption/value/unknown, challenge each other for one bounded round, and yield a chair memo that preserves dissent. It corrects charters from outcomes; it never pretends to be a digital twin. Later (README "voice/persona presentation"), the council can present itself as owner-designed characters, each with its own Voice Studio voice, holding a spoken discussion of the owner's decision with him, grounded in his motto and philosophy. Merged features (owner direction 2026-10-20): the characters live as small always-on-top **desktop pets** on the Windows desktop; **Jarvis and Alfred** (from `features/jarvis-and-alfred/`) are two resident council voices with executive-assistant duties over calendar and tasks (read-only, drafts behind approval); **Parallel Presence Companions** (from `features/parallel-presence-companions/`) become pet-hosted body-doubling focus sessions; the council core stays a headless, testable Python CLI + local API. | E78: Personal ops | F78: CLI → web journal | G78: SvelteKit, Tauri, SQLite | H78: Windows desktop (Tauri pets) + headless core | I78: DCC tab | J78: Personal | K78: Personal → Open-source | L78: High | M78: Medium | N78: Multi-voice council; Jarvis/Alfred desktop pets voiced by Voice Studio; body-doubling focus sessions. | O78: https://github.com/snknitin/motto-agent-council | Q78: 3 blocking · 8 questions · 4 proposals
A79: npc-mode-personal-coach | B79: Merged → feature | C79: paper-logbook | D79: A playful, local-first daily coach that compares today's actual behavior with a user-authored "ideal player character" (chosen values + repeatable behaviors), turns the biggest gap into one executable quest chain, and drafts low-risk admin actions for approval. Momentum, not shame: comparison language describes state ("two tasks are blocked"), never identity. Per README it is a **view over the same task truth as Goal-to-Calendar Planner**, not a second task system. | E79: Personal ops | F79: — | G79: Expo, FastAPI, OR-Tools, SQLite | H79: — | I79: Feature of host | J79: Personal | K79: — | L79: — | M79: — | N79: NPC Mode interstitial-journaling tab of Paper Logbook. | O79: https://github.com/snknitin/npc-mode-personal-coach | Q79: —
A80: paper-logbook | B80: Greenfield · host | C80: absorbs measure-life, brainrot-rehab, npc-mode-personal-coach | D80: An offline-first, paper-like daily/monthly notebook: design a page once (checkboxes, counters, ratings, text, later ink), then live inside it every day with near-zero chrome. Month one deliberately ships one opinionated daily page — not a template studio. It absorbs Measure Life as the **Insights** feature (time-lagged associations and N-of-1 experiments over logbook data), Brainrot Rehab as the **Rehab** feature (a screen-time experiment pack with in-app check-ins), and NPC Mode Personal Coach as the **NPC Mode** feature (interstitial journaling between tasks, prompted at calendar/plan transitions, with a playful "today's script vs what you played" comparison), in the same app and database. One app, two surfaces: the standalone phone app (offline-first, sends transition prompts from Google Calendar + the decided schedule) and a **Dashboard Command Center tab** (group Personal) served by a small tailnet-only sync service on FirstSpark (port 8769) that keeps both surfaces on one event log. | E80: Personal ops | F80: Phone app (Expo) | G80: Expo, expo-sqlite, React Native Skia | H80: Phone + FirstSpark sync (:8769) + DCC tab | I80: Phone app | J80: Personal | K80: Commercial | L80: Medium | M80: High | N80: Paid-once notebook app; 5 views incl. NPC Mode interstitial journaling; calendar-driven prompts. | O80: https://github.com/snknitin/paper-logbook | Q80: 2 blocking · 13 questions · 0 proposals
A81: parallel-presence-companions | B81: Merged → feature | C81: motto-agent-council | D81: A body-doubling focus room: the user declares the next visible task, runs a session with either a real partner or a clearly-labeled synthetic original character, gets lightweight checkpoint check-ins (progress / blocker / next action), and ends with a receipt. Ambient presence, not conversation. | E81: Personal ops | F81: — | G81: SvelteKit, Tauri, SQLite | H81: — | I81: Feature of host | J81: Personal | K81: — | L81: — | M81: — | N81: Body doubling via the always-on desktop pets. | O81: https://github.com/snknitin/parallel-presence-companions | Q81: —
A82: personal-color-relighting-studio | B82: Greenfield | D82: A local-first, mobile-first web studio that turns a calibrated selfie into a private digital draping room: unchanged-face A/B fabric-drape trials rank clothing colors along temperature/value/chroma/contrast with uncertainty, producing a "color passport"; a later depth-aware TypeGPU renderer previews garments under explicitly simulated light. The useful output is ranked axes with evidence — a season label is only a summary. | E82: Personal ops | F82: Mobile-first web | G82: FastAPI, Playwright, React | H82: Phone browser | I82: Standalone web | J82: — | K82: Personal → Commercial | L82: Medium | M82: Medium | N82: Personal color analysis is a paid consumer niche. | O82: https://github.com/snknitin/personal-color-relighting-studio | Q82: 0 blocking · 2 questions · 0 proposals
A83: personalized-adhd-skill-upgrade | B83: Greenfield | D83: Upgrade the existing `i-have-adhd` skill from generic productivity advice to a small, evidence-tracked repertoire: it recognizes the current blockage state, deterministically routes to one user-tested protocol (with fallback), leads with a physical action, and asks for a one-tap outcome review. The canonical output is a revised skill package, personal reference files, fixtures, and a changelog — not an app. | E83: Personal ops | F83: Skill | G83: — | H83: Claude Code / Codex / Hermes | I83: Skill | J83: — | K83: Personal → Open-source | L83: Medium | M83: Low | N83: Upgrade to your i-have-adhd skill. | O83: https://github.com/snknitin/personalized-adhd-skill-upgrade | Q83: 0 blocking · 2 questions · 1 proposals
A84: physio-atlas | B84: Greenfield | D84: A local-first mobile app that organizes already-prescribed or self-selected physio exercises: tap a body region, see reviewed exercise cards with provenance and contraindication notes, assemble a routine, play it, and log reps/load/effort/pain/notes, with trends and a clinician-readable export. Saved social videos are private bookmarks, never redistributed media. | E84: Personal ops | F84: Phone app (Expo) | G84: Expo, SQLite, React | H84: Phone | I84: Phone app | J84: — | K84: Personal → Commercial | L84: Medium | M84: Medium | N84: Exercise organizer with clinician export. | O84: https://github.com/snknitin/physio-atlas | Q84: 0 blocking · 1 questions · 0 proposals
A85: pocket-crm | B85: Parked (archived) | C85: dunbar-dossier (idea note) | D85: Telegram-captured personal CRM with confirm-before-save and a daily follow-up list. | E85: Personal ops | F85: — | G85: — | H85: — | I85: Archived | J85: — | K85: — | L85: — | M85: — | N85: Future Telegram capture front-end for dunbar-dossier. | O85: https://github.com/snknitin/pocket-crm | Q85: —
A86: reflective-eliza-companion | B86: Greenfield | D86: A private, local-first reflective conversation companion: ELIZA-style listening backed by durable, user-auditable memory (facts, preferences, hypotheses, open threads, experiments), with every inference revisable and deletable. It serves one user on their own machine. It must never claim clinical authority, conceal model uncertainty, or optimize for longer or more frequent chats — sessions end in an optional action, not a hook. | E86: Personal ops | F86: Desktop app (Tauri) | G86: Tauri, SQLite | H86: Windows desktop | I86: Standalone desktop | J86: — | K86: Personal | L86: Medium | M86: Low | N86: Private reflective companion; sensitive, keep personal. | O86: https://github.com/snknitin/reflective-eliza-companion | Q86: 1 blocking · 3 questions · 0 proposals
A87: visual-recipe-book | B87: Greenfield | D87: A local-first PWA + Python service that captures recipes (URL, paste, image), compiles them into a reviewed ingredient-operation dependency graph, and renders deterministic Tabular-Recipe-Notation SVG cards, a canonical reading view, and a kitchen cook mode — a personal cookbook faster to cook from than the source page. The semantic core is the DAG; every view compiles from a pinned RecipeRevision. | E87: Personal ops | F87: PWA + Python service | G87: FastAPI, Playwright, SQLite, React | H87: Phone + Windows | I87: Standalone web | J87: — | K87: Personal → Open-source | L87: High | M87: Medium | N87: Recipe graph + cook mode is a lovable open-source app. | O87: https://github.com/snknitin/visual-recipe-book | Q87: 0 blocking · 1 questions · 0 proposals
A88: auto-gtm-engine | B88: Greenfield | D88: A reusable release-to-market pipeline: a versioned `go-to-market.yaml` lives beside each project's code; on an explicit local tag/command the engine collects product truth (changelog fragments, screenshots, proof clips), derives channel-specific assets through a traceable derivation graph, blocks every claim that lacks proof, presents one approval queue, and exports reviewed bundles to channel folders with an outcome record. "Automatic" = collection, derivation, QA, scheduling — never inventing positioning from a diff. | E88: Publishing | F88: CLI pipeline | G88: Jinja, SQLite | H88: Windows / Spark | I88: CLI | J88: — | K88: Open-source | L88: High | M88: Medium | N88: Per-repo go-to-market.yaml + proof-gated assets; dev-tool open source. | O88: https://github.com/snknitin/auto-gtm-engine | Q88: 0 blocking · 2 questions · 0 proposals
A89: build-in-public-autoposter | B89: Merged → feature | C89: creator-content-engine | E89: Publishing | F89: — | G89: — | H89: — | I89: Feature of host | J89: Publishing | K89: — | L89: — | M89: — | N89: Git-activity idea source. | O89: https://github.com/snknitin/build-in-public-autoposter | Q89: —
A90: creator-content-engine | B90: Greenfield · host | C90: absorbs build-in-public-autoposter, my-agent-posts-about-me, x-profile-autopsy, personal-voice-ghostwriter-and-dm-desk, social-subscription-curator, longform-to-shorts-studio | D90: Human-led content OS for one creator: an idea inbox scored against a private evidence library, a draft generator that turns one approved idea into multi-format drafts with a claim ledger, an editorial Kanban calendar, manual publishing packets, and after-the-fact metrics with a weekly review. Nothing publishes without explicit approval. Merged features — three idea sources feeding the one inbox: **Git activity** (former Build in Public Autoposter: allowlisted repo commits + build note), **Daily log** (former My Agent Posts About Me: private hand-authored journal observations), and **Profile autopsy** (former X Profile Autopsy: a tab analyzing your own X posts into pillars, gaps, and ideas); all keep their secret/privacy scanning and evidence links, and none of them publishes anything. Wave 2 (owner direction 2026-10-20) makes it the owner's one content, branding, visibility and social-interaction OS — one Dashboard Command Center tab (group **Publishing**) with five more areas: **Voice** (former Personal Voice Ghostwriter: an inspectable voice model every draft is grounded in, with provenance), **Observe** (a daily collector of the owner's own social activity and followed accounts, reusing TikTok Learning Center, Social Capture, Fresh Brief/FreshRSS and platform exports), **Follow** (former Social Subscription Curator + X Like-to-List Builder: keep/list/mute/unsubscribe proposals and X Lists from likes), **Interact** (former DM Desk: suggested replies, comments and DMs to people the owner follows, drafted in the owner's voice), and **Studio** (former Longform-to-Shorts Studio + Podcast Clips Agency: long video/podcast → clips on the Windows GPU). **Hard rule:** nothing is posted, liked, followed, unfollowed, unsubscribed or sent without the owner's per-item click in this UI; the engine performs no engagement itself. | E90: Publishing | F90: Web dashboard | G90: SvelteKit, Next.js, Streamlit, FastAPI, HTMX, n8n, sentence-transformers, Polars, Playwright, PyTorch, FFmpeg, SQLite, React, Docker | H90: Windows desktop + FirstSpark collector (:8770) | I90: DCC tab | J90: Publishing | K90: Personal → Commercial | L90: Medium | M90: High | N90: One content/branding/social OS: voice, observe, follow, interact (human-approved), studio. | O90: https://github.com/snknitin/creator-content-engine | Q90: 3 blocking · 14 questions · 1 proposals
A91: flex-card-forge | B91: Greenfield | D91: A local Next.js app that turns opt-in GitHub stats plus pasted Strava/Chess.com exports into a collectible SVG/PNG card with inspectable claims: every stat carries provenance, and rarity is an honest percentile against a fixed, named cohort snapshot. Serves the owner's own profiles only. | E91: Publishing | F91: Web app (Next.js) | G91: Next.js, Playwright, SQLite | H91: Windows desktop | I91: Standalone web | J91: — | K91: Open-source / viral | L91: Medium | M91: Medium | N91: Shareable stat cards with honest provenance. | O91: https://github.com/snknitin/flex-card-forge | Q91: 1 blocking · 1 questions · 0 proposals
A92: landing-page-conversion-agency | B92: Greenfield · host | C92: absorbs roast-my-landing-page | D92: A local CRO workbench that audits a user-OWNED landing page: captures desktop/mobile screenshots, runs Lighthouse + axe-core, extracts copy, links every finding to evidence, proposes ranked rewrites into an editable preview, and exports an experiment brief. It separates measured problems from hypotheses and never promises uplift without an experiment. It also hosts the merged **Roast** feature (from `roast-my-landing-page`): a funny, privacy-safe "evidence → joke → fix" share card built over the same audit evidence, plus a screenshot + hero-copy quick-roast intake. | E92: Publishing | F92: Web dashboard | G92: Next.js, Playwright, SQLite | H92: Windows desktop | I92: DCC tab | J92: Publishing | K92: Commercial | L92: Medium | M92: High | N92: Evidence-backed CRO audits; the roast card is a free viral funnel into it. | O92: https://github.com/snknitin/landing-page-conversion-agency | Q92: 0 blocking · 3 questions · 0 proposals
A93: microsite-factory | B93: Greenfield | D93: A schema-driven factory that turns approved, cited account research into consistent static microsites from one shared Astro template, passes them through automated QA gates (schema, links, accessibility, Lighthouse, screenshots), and deploys approved pages as private Cloudflare Pages previews. One codebase, N validated content files — never twenty divergent sites. | E93: Publishing | F93: Astro pipeline + Cloudflare | G93: Astro, Playwright, Cloudflare, SQLite | H93: Windows + Cloudflare | I93: CLI + hosted previews | J93: Publishing | K93: Commercial | L93: Medium | M93: Medium | N93: One template, N validated account sites. | O93: https://github.com/snknitin/microsite-factory | Q93: 0 blocking · 2 questions · 0 proposals
A94: my-agent-posts-about-me | B94: Merged → feature | C94: creator-content-engine | E94: Publishing | F94: — | G94: — | H94: — | I94: Feature of host | J94: Publishing | K94: — | L94: — | M94: — | N94: Daily-log idea source. | O94: https://github.com/snknitin/my-agent-posts-about-me | Q94: —
A95: personal-voice-ghostwriter-and-dm-desk | B95: Merged → feature | C95: creator-content-engine | D95: A local-first writing desk that drafts public posts (X, LinkedIn) and private DM replies in the owner's actual voice, grounded in curated Obsidian/Notion sources with heading-level provenance, relationship cards with promises/open loops, and an inspectable voice card that learns from accepted edit diffs. Every factual/personal claim cites a source or is flagged for user input. Public and private modes share the voice primitives but never each other's data. | E95: Publishing | F95: — | G95: SvelteKit, FastAPI, SQLite | H95: — | I95: Feature of host | J95: Publishing | K95: — | L95: — | M95: — | N95: Voice + DM desk of Creator Content Engine. | O95: https://github.com/snknitin/personal-voice-ghostwriter-and-dm-desk | Q95: —
A96: roast-my-landing-page | B96: Merged → feature | C96: landing-page-conversion-agency | E96: Publishing | F96: — | G96: — | H96: — | I96: Feature of host | J96: Publishing | K96: — | L96: — | M96: — | N96: Roast mode share card. | O96: https://github.com/snknitin/roast-my-landing-page | Q96: —
A97: seo-agency-crew | B97: Greenfield | D97: A local, evidence-led editorial workbench for an owned site: crawl/inventory the site, cluster queries into topic briefs, draft source-grounded pages with validated citations, build an internal-link graph, audit quality (Lighthouse/axe), and preview in Astro — publishing only after page-level human approval with a visible diff. V0 serves the owner's own blog/notes as a learning lab. | E97: Publishing | F97: Web dashboard + Astro | G97: Astro, sentence-transformers, Polars, SQLite | H97: Windows desktop | I97: DCC tab | J97: Publishing | K97: Commercial | L97: Medium | M97: Medium | N97: Evidence-led editorial workbench. | O97: https://github.com/snknitin/seo-agency-crew | Q97: 1 blocking · 1 questions · 0 proposals
A98: shopify-product-page-optimizer | B98: Greenfield | D98: A local audit dashboard + copy generator: import an owned product page (saved HTML/URL/export) plus an approved product-facts sheet, audit structure and completeness, and produce an evidence-constrained upgrade package — title, bullets, FAQ, trust structure, SEO title/meta, alt text, image brief — as an exact before/after patch the merchant reviews side by side. | E98: Publishing | F98: Web dashboard | G98: Next.js, Playwright, SQLite | H98: Windows desktop | I98: Standalone / DCC tab | J98: Publishing | K98: Commercial | L98: Low | M98: High | N98: Kept separate by your choice; natural Shopify-app product. | O98: https://github.com/snknitin/shopify-product-page-optimizer | Q98: 0 blocking · 2 questions · 0 proposals
A99: x-profile-autopsy | B99: Merged → feature | C99: creator-content-engine | E99: Publishing | F99: — | G99: — | H99: — | I99: Feature of host | J99: Publishing | K99: — | L99: — | M99: — | N99: Profile-analysis tab. | O99: https://github.com/snknitin/x-profile-autopsy | Q99: —
A100: bionic-reading-trainer | B100: Greenfield | D100: An on-device PWA reading surface: paste text, tune fixation emphasis (bold-prefix length), line width, font, contrast, chunk size and pacing, read in three modes, and log comprehension so the visual treatment adapts to the reader. Serves one reader studying/skimming on their own device; everything stays local. | E100: Reading | F100: PWA | G100: SvelteKit, React | H100: Any browser / phone | I100: Standalone web | J100: — | K100: Open-source | L100: High | M100: Low | N100: Small, on-device, privacy-first: ideal open-source utility. | O100: https://github.com/snknitin/bionic-reading-trainer | Q100: 0 blocking · 1 questions · 0 proposals
...

Sheet Merges
A1: Project | B1: Status | C1: Now lives in | D1: Note
A2: am-i-underpaid | B2: Merged → feature | C2: jobs-search-and-apply-tool | D2: Comp-check tab that feeds the compensation floor.
A3: ai-event-matchmaker | B3: Merged → feature | C3: event-ops-agency | D3: Attendee matchmaking tab.
A4: google-review-reply-desk | B4: Merged → feature | C4: customer-support-agency | D4: Public review replies tab.
A5: paid-ad-account-audit | B5: Merged → feature | C5: meta-ad-creative-studio | D5: Audit tab.
A6: support-faq-builder | B6: Merged → feature | C6: customer-support-agency | D6: Deduplicated into the support pipeline.
A7: pr-factory | B7: Merged → feature | C7: maintainer-desk | D7: Patch-tournament engine.
A8: 27-clicks-to-cancel | B8: Merged → feature | C8: paisa-vasool-subscriptions | D8: Cancel-assist step inside Paisa.
A9: edge-desk | B9: Merged → feature | C9: event-market-research-terminal | D9: Its alerts and ambiguity warnings now live in EMRT.
A10: invoice-chaser-agent | B10: Merged → feature | C10: finance-ops-agency | D10: Receivables/chase tab inside Finance Ops.
A11: latte-into-lambo | B11: Merged → feature | C11: net-worth-command-center | D11: Now Net Worth's What-if tab.
A12: market-mood-cards | B12: Merged → feature | C12: finance-signals-dashboard | D12: Morning tab of Finance Signals.
... A48: startup-graveyard | B48: Merged → feature | C48: side-hustle-radar | D48: Failure-research tab.

Sheet DCC Groups
A1: DCC group | B1: Dashboards in group (live count) | C1: Members
A2: Money | B2: =COUNTIFS(Portfolio!$J$2:$J$139,A2,Portfolio!$I$2:$I$139,"DCC*")+COUNTIFS(Portfolio!$J$2:$J$139,A2,Portfolio!$I$2:$I$139,"Standalone / DCC tab") | C2: event-market-research-terminal, finance-ops-agency, finance-signals-dashboard, net-worth-command-center, paisa-vasool-subscriptions, personal-finance-cockpit
A3: Career | B3: =COUNTIFS(Portfolio!$J$2:$J$139,A3,Portfolio!$I$2:$I$139,"DCC*")+COUNTIFS(Portfolio!$J$2:$J$139,A3,Portfolio!$I$2:$I$139,"Standalone / DCC tab") | C3: jobs-search-and-apply-tool, mock-interview-gauntlet, resume-blueprint-studio
A4: Learning | B4: =COUNTIFS(Portfolio!$J$2:$J$139,A4,Portfolio!$I$2:$I$139,"DCC*")+COUNTIFS(Portfolio!$J$2:$J$139,A4,Portfolio!$I$2:$I$139,"Standalone / DCC tab") | C4: kaggle-learning-center, personal-study-curriculum, quiz-master, tiktok-learning-center, youtube-learning-center
A5: Signals | B5: =COUNTIFS(Portfolio!$J$2:$J$139,A5,Portfolio!$I$2:$I$139,"DCC*")+COUNTIFS(Portfolio!$J$2:$J$139,A5,Portfolio!$I$2:$I$139,"Standalone / DCC tab") | C5: fresh-brief, social-capture
A6: Publishing | B6: =COUNTIFS(Portfolio!$J$2:$J$139,A6,Portfolio!$I$2:$I$139,"DCC*")+COUNTIFS(Portfolio!$J$2:$J$139,A6,Portfolio!$I$2:$I$139,"Standalone / DCC tab") | C6: creator-content-engine, landing-page-conversion-agency, seo-agency-crew, shopify-product-page-optimizer
A7: Ventures | B7: =COUNTIFS(Portfolio!$J$2:$J$139,A7,Portfolio!$I$2:$I$139,"DCC*")+COUNTIFS(Portfolio!$J$2:$J$139,A7,Portfolio!$I$2:$I$139,"Standalone / DCC tab") | C7: ai-implementation-agency, competitive-intelligence-agency, deal-desk-agency, demand-generation-workbench, sales-development-agency, side-hustle-radar, user-research-agency
A8: Client services | B8: =COUNTIFS(Portfolio!$J$2:$J$139,A8,Portfolio!$I$2:$I$139,"DCC*")+COUNTIFS(Portfolio!$J$2:$J$139,A8,Portfolio!$I$2:$I$139,"Standalone / DCC tab") | C8: community-ops-agency, customer-support-agency, event-ops-agency, knowledge-base-agency, meta-ad-creative-studio, recruiting-agency
A9: Personal | B9: =COUNTIFS(Portfolio!$J$2:$J$139,A9,Portfolio!$I$2:$I$139,"DCC*")+COUNTIFS(Portfolio!$J$2:$J$139,A9,Portfolio!$I$2:$I$139,"Standalone / DCC tab") | C9: daily-parent-check-in, dunbar-dossier, inbox-zero-mercenary, motto-agent-council
A10: Dev | B10: =COUNTIFS(Portfolio!$J$2:$J$139,A10,Portfolio!$I$2:$I$139,"DCC*")+COUNTIFS(Portfolio!$J$2:$J$139,A10,Portfolio!$I$2:$I$139,"Standalone / DCC tab") | C10: agents-board, maintainer-desk, on-call-autopilot
A11: Studio | B11: =COUNTIFS(Portfolio!$J$2:$J$139,A11,Portfolio!$I$2:$I$139,"DCC*")+COUNTIFS(Portfolio!$J$2:$J$139,A11,Portfolio!$I$2:$I$139,"Standalone / DCC tab")
A12: Labs | B12: =COUNTIFS(Portfolio!$J$2:$J$139,A12,Portfolio!$I$2:$I$139,"DCC*")+COUNTIFS(Portfolio!$J$2:$J$139,A12,Portfolio!$I$2:$I$139,"Standalone / DCC tab")

Sheet Summary
A1: Projects in portfolio | B1: =COUNTA(Portfolio!A2:A139)
A3: By status
A4: Brownfield (live) | B4: =COUNTIF(Portfolio!$B$2:$B$139,A4)
A5: Built elsewhere | B5: =COUNTIF(Portfolio!$B$2:$B$139,A5)
A6: Greenfield | B6: =COUNTIF(Portfolio!$B$2:$B$139,A6)
A7: Greenfield · host | B7: =COUNTIF(Portfolio!$B$2:$B$139,A7)
A8: Kept (ideas ported) | B8: =COUNTIF(Portfolio!$B$2:$B$139,A8)
A9: Merged → feature | B9: =COUNTIF(Portfolio!$B$2:$B$139,A9)
A10: Parked (archived) | B10: =COUNTIF(Portfolio!$B$2:$B$139,A10)
A11: Retired (archived) | B11: =COUNTIF(Portfolio!$B$2:$B$139,A11)
A12: Third-party | B12: =COUNTIF(Portfolio!$B$2:$B$139,A12)
A13: Total | B13: =SUM(B4:B12)
A15: By best use
A16: Archived | B16: =COUNTIF(Portfolio!$I$2:$I$139,A16)
A17: Browser extension | B17: =COUNTIF(Portfolio!$I$2:$I$139,A17)
A18: CLI | B18: =COUNTIF(Portfolio!$I$2:$I$139,A18)
A19: CLI + Obsidian | B19: =COUNTIF(Portfolio!$I$2:$I$139,A19)
A20: CLI + hosted previews | B20: =COUNTIF(Portfolio!$I$2:$I$139,A20)
A21: DCC group | B21: =COUNTIF(Portfolio!$I$2:$I$139,A21)
A22: DCC tab | B22: =COUNTIF(Portfolio!$I$2:$I$139,A22)
A23: Excluded | B23: =COUNTIF(Portfolio!$I$2:$I$139,A23)
A24: Feature of host | B24: =COUNTIF(Portfolio!$I$2:$I$139,A24)
A25: Hosted product | B25: =COUNTIF(Portfolio!$I$2:$I$139,A25)
A26: Hosted web | B26: =COUNTIF(Portfolio!$I$2:$I$139,A26)
A27: Lab harness | B27: =COUNTIF(Portfolio!$I$2:$I$139,A27)
... A37: The hub itself | B37: =COUNTIF(Portfolio!$I$2:$I$139,A37)
A38: Total | B38: =SUM(B16:B37)
A40: By commercial fit
A41: High | B41: =COUNTIF(Portfolio!$M$2:$M$139,A41)
A42: Medium | B42: =COUNTIF(Portfolio!$M$2:$M$139,A42)
A43: Low | B43: =COUNTIF(Portfolio!$M$2:$M$139,A43)
A44: Total | B44: =SUM(B41:B43)
A46: By open-source fit
A47: High | B47: =COUNTIF(Portfolio!$L$2:$L$139,A47)
A48: Medium | B48: =COUNTIF(Portfolio!$L$2:$L$139,A48)
A49: Low | B49: =COUNTIF(Portfolio!$L$2:$L$139,A49)
A50: Total | B50: =SUM(B47:B49)

Sheet Legend
A1: Item | B1: Meaning
A2: Source of truth | B2: scripts/portfolio/portfolio.csv. This workbook and Project Portfolio.md are generated by build_portfolio.py.
A3: Your notes (yellow) | B3: Type in column P; the next build copies them into portfolio.csv. Edits to other columns are overwritten — change those in portfolio.csv.
A4: Open questions | B4: Counted from each spec's §6, the same items handoff_questions.py writes into REPORT.md for the Agents board.
A5: Status | B5: Brownfield (live) = real code. Greenfield = README + spec. Greenfield · host = also absorbs merged features. Merged → feature = lives at <host>/features/<name>/. Parked/Retired = archived on GitHub. Built elsewhere = finished outside E:\GIT_ROOT\Projects.
A6: Fit scores | B6: Judgment calls (High/Medium/Low) from each README's product path, market and privacy constraints; not market research.
